GuechaouiMohamed_reg/GuechaouiMohamed_reg.py
GuechaouiMohamed_reg/__init__.py
GuechaouiMohamed_reg-1.0.0.dist-info/METADATA
GuechaouiMohamed_reg-1.0.0.dist-info/WHEEL
GuechaouiMohamed_reg-1.0.0.dist-info/top_level.txt
GuechaouiMohamed_reg-1.0.0.dist-info/RECORD
