Metadata-Version: 2.1
Name: GuechaouiMohamed_reg
Version: 1.0.0
Summary: A Python package for implementing a Simple Linear Regression model
Home-page: http://pypi.python.org/pypi/GuechaouiMohamed_reg/
Author: Mohamed Guechaoui
Author-email: m.guechaoui@esi-sba.dz
License: LICENSE.txt
